authwert/PROJECT.txt
authwert/__init__.py
authwert/etc/auth-wordpress.py
authwert/web/login.html
authwert/web/logout.html
authwert-0.1.5.data/scripts/authwert
authwert-0.1.5.dist-info/LICENSE
authwert-0.1.5.dist-info/METADATA
authwert-0.1.5.dist-info/WHEEL
authwert-0.1.5.dist-info/top_level.txt
authwert-0.1.5.dist-info/RECORD
