Metadata-Version: 2.1
Name: authwert
Version: 0.1.5
Summary: Simple Authenticator
Home-page: https://github.com/wheresjames/authwert
Author: Robert Umbehant
Author-email: authwert@wheresjames.com
License: MIT
Platform: UNKNOWN
License-File: LICENSE
Requires-Dist: aiohttp
Requires-Dist: argparse
Requires-Dist: cryptography
Requires-Dist: dateparser
Requires-Dist: propertybag
Requires-Dist: pyjwt
Requires-Dist: sparen
Requires-Dist: webshoes (>=0.1.4)
